iiif_tools/__init__.py
iiif_tools/_modidx.py
iiif_tools/core.py
iiif_tools/pdf.py
iiif_tools-0.0.3.dist-info/LICENSE
iiif_tools-0.0.3.dist-info/METADATA
iiif_tools-0.0.3.dist-info/WHEEL
iiif_tools-0.0.3.dist-info/entry_points.txt
iiif_tools-0.0.3.dist-info/top_level.txt
iiif_tools-0.0.3.dist-info/RECORD
